{"wantInvite_NewUserAct": 0, "openBetaAreaAtMinePg": 1, "transferMoreInfo": 2, "rules_NewUserAct": 3, "Web": 425, "quickPassSubmit": 674, "309AtBanner": 4, "messageAtIdxMainPg": 5, "safequs_reset_input_ans": 6, "F10_21_L2279AtMallHome": 7, "usedCpnAtMinePg": 8, "city_select": 427, "WalletPayPlugin": 10, "579AtLifeChnlPg": 11, "700AtIdxMainPg": 798, "bankAccountOutSucc": 13, "432AtActTheme": 14, "up99_promotion_share_weChat": 705, "chinaTelecomFeePayConfirm": 15, "filterEntry": 16, "429AtHotPay": 17, "F15_6_L2521AtMallHome": 18, "F8_19_L2302AtMallHome": 19, "myReward_QPReward": 78, "creditCardPayAmount": 21, "F14_4_M1AtMallHome": 124, "468AtIdxMainPg": 23, "765AtIdxMainPg": 24, "bankAccountIntoConfirm": 25, "F12_2_L2529AtMallHome": 26, "transferMoneyFail": 27, "457AtActTheme": 28, "logoutSuccess": 29, "LoginView": 30, "F8_19_M1AtMallHome": 183, "694AtLifeChnlPg": 32, "UPQRPaySuccessActivity": 33, "creditCardPayPg": 34, "ChooseExistCard": 35, "gasFeePaySuccess": 36, "187AtIdxMainPg": 580, "PointSetting": 38, "saveShoukuanCode": 39, "haveGot_NewYearAct": 40, "setPayPassword": 41, "MyQueryBalance": 42, "IdentityInfo": 43, "taxRebateInquiry": 44, "chongyang_inviteView_wantInvite": 45, "startGet_NewYearAct": 46, "myReward_P2PActPg": 47, "inviteReord_NewUserAct": 48, "bindcardRealAuthenUnsupport": 49, "myFavoAtMinePg": 50, "CommonCourtesyView": 51, "saomaPayFail": 52, "toCardDetail": 53, "472AtIdxMainPg": 731, "WalletPayPasswordVerify": 54, "62AtIdxMainPg": 55, "win_NewUserAct": 57, "transferMoneyPg": 297, "share_QPReward": 59, "mnAtTransHP": 60, "transferReceiveCardSet": 61, "mobileFeePaySuccess": 434, "F12_2_L2530AtMallHome": 63, "transferRecord": 64, "unuseCpnAtMinePg": 830, "logoutApply": 445, "fukuanHome": 65, "localServicePg": 368, "F11_9_L2278AtMallHome": 67, "topright_saoma": 68, "applyCardSubmit": 69, "safequs_reset_select_qus": 66, "toPayAuth_NewYearAct": 72, "PatternLockView": 73, "PayActivity": 74, "feedbackAtMinePg": 75, "329AtIdxMainPg": 76, "CardManagerClick": 77, "signShare_NewYearAct": 79, "virtualAcctAdd": 80, "F1_31_L2549AtMallHome": 584, "transDetailPg": 82, "BillDownloadResultView": 83, "B5_188AtMallHomePg": 84, "NewCard": 85, "reward_P2PActPg": 687, "toSetPay": 86, "event_id:openBetaPgEnter": 87, "I2_163AtMallHomePg": 88, "activityAtIdxMainPg": 89, "buyCouponSuccess": 90, "CouponChnlPg": 430, "564AtIdxMainPg": 92, "PrivilegeList": 93, "cashierAtMinePg": 94, "301AtActTheme": 95, "crdBalInqBtn": 96, "F17_7_L2502AtMallHome": 97, "reset_pwd_submit": 98, "F19_10_L2534AtMallHome": 99, "signSucc_NewYearAct": 100, "bankAccountApplySms": 101, "F17_7_L2457AtMallHome": 103, "479AtIdxMainPg": 104, "myRptAtTransHP": 105, "41brandLst": 106, "107brandLst": 556, "checkLogistics": 107, "chongyang_inviteView_checkReward": 108, "707AtActArea": 292, "bindcardFail": 854, "cloudpayBindcard": 110, "toRealName_NewUserAct": 111, "openSucc_NewYearAct": 112, "543AtIdxMainPg": 113, "bindDefaultCardAppearance": 114, "pwd_reset_input_pwd": 116, "708AtActArea": 703, "549AtBanner": 590, "PasswordSetView": 20, "200AtIdxMainPg": 119, "MyLaboratory": 120, "bankcard_link_input_phoneNO": 121, "174AtHotPay": 744, "billInformation": 123, "refind_pwd_submit": 125, "458AtLifeChnlPg": 126, "685AtIdxMainPg": 843, "aboutAct_QPReward": 745, "707AtIdxMainPg": 128, "bankConf_P2PActPg": 130, "F14_6_L2431AtMallHome": 131, "LifeAppDelegate": 132, "bankAccountOut": 134, "682AtTopBar": 593, "F6_23_L2406AtMallHome": 136, "moduleInLifeStyle": 137, "bankcard_link_select_availdata": 138, "564AtActTheme": 139, "toBankCardLst": 140, "AccountIntoOut": 244, "creditCardPayChoose": 142, "toPayAuth_NewUserAct": 450, "378AtIdxMainPg": 144, "F14_4_L2497AtMallHome": 145, "bankAccountApplySucc": 594, "482AtIdxMainPg": 146, "transferMoneyConfirm": 748, "F18_3_M1AtMallHome": 217, "getClose_NewUserAct": 150, "reset_pwd_fail": 151, "703AtBanner": 152, "refundInOrderDetaiSuccess": 153, "shaidan_action": 154, "B1_194AtMallHomePg": 155, "creditCardPaySubmit": 156, "cloudpayCardNO": 157, "173AtLifeChnlPg": 158, "685AtTopBar": 159, "653AtLifeChnlPg": 160, "F5_27_L2411AtMallHome": 161, "SecurityRelativeView": 162, "488AtIdxMainPg": 163, "F15_1_L2452AtMallHome": 164, "couponFilterOnline": 165, "B1_196AtMallHomePg": 166, "up99_promotion_share_copy": 167, "goodsPara": 176, "MinePg": 169, "DefaultCardSet": 170, "otherCloudCard": 171, "F19_3_L2511AtMallHome": 172, "F9_21_L2281AtMallHome": 600, "296AtActTheme": 752, "F12_9_L2487AtMallHome": 175, "484AtHotPay": 56, "bankCardPrivilegeDetl": 177, "F3_13_L2492AtMallHome": 178, "Paipaicard_eCashRechargeView": 726, "gasFeeInquiry": 179, "F16_1_L2507AtMallHome": 180, "703AtIdxMainPg": 181, "F14_6_L2520AtMallHome": 182, "F10_21_L2281AtMallHome": 184, "creditCardRepayPg": 185, "patternLockByFingerprint": 279, "455AtIdxMainPg": 187, "F11_9_L2484AtMallHome": 284, "B4_188AtMallHomePg": 286, "moreRecharge": 190, "F1_31_L2551AtMallHome": 191, "realNameCancel_NewYearAct": 192, "482AtLifeChnlPg": 193, "F8_18_M1AtMallHome": 194, "WkExpPg": 195, "sysError_NewUserAct": 196, "city_search": 197, "bankCardDtl": 198, "MyPointView": 755, "realnameFail": 201, "serviceAtCouponDtl": 202, "bankcard_link_input_cardNO": 203, "ShareView": 204, "F14_6_M1AtMallHome": 205, "AccountType": 206, "F21_8_L2522AtMallHome": 207, "MySecurityQuestSet": 208, "CardRulesView": 209, "F5_27_L2410AtMallHome": 210, "CouponDtl": 757, "virtualAcctClick": 212, "87brandLst": 213, "SecurityQuestionSetView": 214, "paipaicard_queryBalanceSuccess": 215, "F18_3_L2514AtMallHome": 456, "saomaPayConfirm": 218, "quickPassFail": 759, "F13_4_L2496AtMallHome": 220, "MnExpPg": 221, "E0FilterNative": 222, "QRCodeView": 223, "F8_19_L2100AtMallHome": 224, "gasFeeInquirySuccess": 225, "goodsConfirm": 226, "309AtIdxMainPg": 227, "27AtIdxMainPg": 228, "MyDownloadView": 229, "UPHcePayResult": 230, "WalletPaySuccess": 231, "startDraw_P2PActPg": 232, "bindSelectCardAppearance": 233, "wkAtTransHP": 234, "F15_6_L2431AtMallHome": 235, "shoukuanRecord": 236, "bountyTsmFail": 237, "saveShoukuanCodeSucc": 239, "cloudpayOpenSuccess": 240, "CardDetailView": 241, "432AtIdxMainPg": 242, "139AtIdxMainPg": 243, "F6_23_M1AtMallHome": 133, "B4_192AtMallHomePg": 200, "gasFeePayConfirm": 115, "GuideBindCard": 248, "378AtHotPay": 249, "quickPassNext": 250, "300AtActTheme": 251, "couponFilterNative": 253, "toRealName_NewYearAct": 254, "483AtIdxMainPg": 255, "payAuthCancel_NewYearAct": 256, "fukuanScan": 141, "PointDetailView": 257, "markButton": 258, "myRewardAtMinePg": 259, "bindInputCardNO": 260, "178AtTopBar": 261, "registerApply": 262, "login_user": 263, "bannerAtTransPg": 264, "chinaMobileFeeInquirySuccess": 265, "85AtIdxMainPg": 266, "getAgain_NewUserAct": 267, "BrandLstPg": 269, "chinaUnicomFeeInquiry": 270, "704AtLifeChnlPg": 271, "fukuanPassword": 272, "BookkeepingGraphicView": 273, "F21_8_M1AtMallHome": 274, "goodsGraph": 275, "pwd_reset_submit": 852, "F19_10_L2543AtMallHome": 276, "localServiceSearch": 277, "CardItemSelection": 278, "unionpaywalletPay": 700, "701AtBanner": 186, "strategy_P2PAct": 280, "loginSuccess": 281, "F12_9_L2542AtMallHome": 282, "ATMView": 283, "fukuanRefresh": 188, "350AtLifeChnlPg": 285, "F19_10_L2536AtMallHome": 189, "returnApply": 772, "765AtHotPay": 287, "electricFeeInquirySuccess": 288, "701AtIdxMainPg": 289, "creditCardPayMore": 753, "692AtLifeChnlPg": 291, "myMoreAtMinePg": 109, "drawReord_NewUserAct": 293, "MainCityView": 294, "334AtLifeChnlPg": 623, "85AtBanner": 296, "openShare_NewYearAct": 58, "bindcardCardno": 773, "DefaultAPP": 299, "Certification": 300, "cloudCardBindcard": 774, "F2_30_L2547AtMallHome": 302, "freeGetCouponFail": 303, "163AtActTheme": 304, "getSucc_QPReward": 306, "489AtIdxMainPg": 307, "AccountOpen": 308, "I1_153AtMallHomePg": 309, "180AtIdxMainPg": 310, "openBetaDisclaimer": 625, "ScanPanView": 312, "getCpnAtActCpn": 313, "bankCardEdit": 315, "myMsgAtMinePg": 316, "F8_18_L2052AtMallHome": 319, "VerifyCode": 320, "478AtLifeChnlPg": 321, "473AtIdxMainPg": 627, "163AtIdxMainPg": 323, "WelcomeView": 324, "474AtIdxMainPg": 268, "fukuanInstr": 327, "CrdDtlPg_virtual": 328, "455AtActTheme": 329, "472AtLifeChnlPg": 330, "489AtActTheme": 331, "BankCard": 332, "F2_16_L2269AtMallHome": 333, "F8_18_L2053AtMallHome": 335, "AddCardView": 337, "180AtBanner": 338, "179AtIdxMainPg": 339, "creditCardPaySuccess": 340, "C0FilterOnline": 341, "HomeCourtesyView": 342, "CrdLstPg": 343, "201AtActTheme": 238, "690AtLifeChnlPg": 345, "cloudpayGuide": 346, "484AtIdxMainPg": 347, "bindUnionPaySubmit": 348, "IdxMainPg": 350, "newOnline": 495, "transferReceiveCard": 352, "H1_162AtMallHomePg": 353, "FeedBackView": 354, "bindUnionPayConfirm": 355, "F19_10_M1AtMallHome": 356, "anlsToDtl": 357, "mobileFeeStart": 358, "myOrdrAtMinePg": 359, "472AtHotPay": 360, "693AtLifeChnlPg": 362, "bankcard_link_apply": 363, "bankAccountApply": 364, "39brandLst": 365, "chinaMobileFeePayConfirm": 366, "login_pwd": 367, "bankAccountIntoSucc": 369, "187AtActTheme": 370, "exchangeSubmit": 148, "F16_1_L2452AtMallHome": 326, "crdtCrdRepay": 372, "79AtIdxMainPg": 373, "event_id:openBetaReject": 374, "goodsHelpApply": 375, "C0FilterNative": 376, "NewUserActPg": 377, "_AddAccountDetail": 378, "applCrdPg": 379, "auickPassSelectCard": 380, "anlsToDtl_virtual": 381, "secAtMinePg": 382, "OrderDtlPg": 383, "F16_1_M1AtMallHome": 384, "messageCenter": 385, "functionInCardDetail": 386, "F9_19_L2101AtMallHome": 387, "cardRealnameFail": 388, "applyCardApply": 389, "freeGetCouponSuccess": 390, "bankAccountSelectCard": 391, "102AtLifeChnlPg": 392, "481AtIdxMainPg": 624, "changeCardTransferMoney": 469, "newCreditCardAdd": 394, "event_id:openBetaAgree": 344, "PayPasswordSet": 638, "taxRebateCountry": 397, "bankcard_link_click_get_msg": 398, "reset_pwd_success": 399, "StoreDtl": 400, "F14_6_L2521AtMallHome": 401, "bankShare_P2PActPg": 402, "F8_19_L2101AtMallHome": 736, "468AtHotPay": 403, "F6_27_L2411AtMallHome": 404, "F14_4_L2499AtMallHome": 405, "DefaultCardSetConfirm": 406, "F2_16_L2271AtMallHome": 407, "chinaTelecomFeePaySuccess": 408, "goodsDetlPg": 409, "relativesGiveMoney": 410, "587AtActTheme": 411, "MyCostRecordView": 412, "bindcardSuccess": 413, "F7_18_M1AtMallHome": 414, "myExpAtTransHP": 416, "F4_15_L2277AtMallHome": 417, "bankcard_link_input_msg": 418, "bankCardPrivilege": 419, "toVirtualAcctPreview": 420, "win_P2PActPg": 421, "479AtHotPay": 422, "merchAround_QPReward": 423, "exprCpnAtMinePg": 424, "F15_1_L2507AtMallHome": 325, "myRewardPg_QPReward": 426, "CardSMSServiceView": 9, "openBetaFeedbackSubmit": 428, "toCardDetail_virtual": 91, "MoreView": 431, "bankcard_link_input_cardNO_next": 432, "702AtBanner": 433, "A0FilterNative": 62, "F16_5_L2532AtMallHome": 435, "EditAvartaView": 436, "saomaPhoto": 437, "orderApplyAgain": 438, "realnameSuccess": 439, "signFail_NewYearAct": 440, "105brandLst": 441, "BrandDtl": 443, "startDraw_NewUserAct": 444, "TdyExpPg": 118, "safequs_reset_submit": 446, "B7_188AtMallHomePg": 447, "editAtTransSysPg": 129, "F19_3_L2313AtMallHome": 449, "F2_16_M1AtMallHome": 143, "goodsPrice": 149, "guideCancel_NewYearAct": 452, "bankAccountApplyCard": 453, "Paipaicard_HomeView": 454, "F19_3_L2513AtMallHome": 455, "302AtActTheme": 457, "transferMoney": 458, "creditCardRepayMore": 459, "F2_30_L2548AtMallHome": 460, "PrivilegeMain": 461, "F6_23_L2404AtMallHome": 462, "F12_9_M1AtMallHome": 463, "FillLoginMobileView": 464, "reset_welcome_info": 465, "MyOrderView": 466, "B0FilterNative": 467, "F18_3_L2511AtMallHome": 393, "F14_4_L2544AtMallHome": 470, "youhui_share": 471, "timeFilterSubmit": 472, "706AtLifeChnlPg": 473, "taxRebateStrategy": 474, "UPHceActivityCardRules": 12, "fukuanSuccess": 448, "F0FilterNative": 476, "realnameSubmit": 477, "10AtIdxMainPg": 478, "creditCardPayAmountConfirm": 479, "P2PLotteryAtTransferMoney": 480, "youhui_search": 481, "F8_19_L2407AtMallHome": 482, "fukuanWithoutPwd": 483, "65AtTopBar": 484, "pwd_reset_fail": 485, "68brandLst": 442, "FeedbackView": 487, "saomaSuccess": 488, "QPRewardPg": 489, "myIDAtMinePg": 490, "F21_8_L2523AtMallHome": 429, "B5_193AtMallHomePg": 492, "F10_21_L2282AtMallHome": 493, "openBetaPgEnter": 494, "UpdateUserInfoView": 656, "174AtIdxMainPg": 351, "goodsHelpTab": 617, "applyCardPg": 497, "UPHceActivityActviate": 603, "F18_3_L2515AtMallHome": 499, "MyMessageView": 658, "99brandLst": 501, "setPayPasswordPg": 502, "crdBalInqSucc": 503, "Paipaicard_DebitCardDetailView": 504, "F9_19_L2302AtMallHome": 505, "bindTakeCardNOConfirm": 506, "exchangeReturn": 252, "F9_21_L2282AtMallHome": 636, "F1_30_L2545AtMallHome": 509, "registerPwd": 510, "safequs_reset_fail": 511, "F13_4_L2499AtMallHome": 513, "billRmdAtMinePg": 802, "697AtActTheme": 512, "F11_9_L2486AtMallHome": 514, "EditCardFace": 515, "F2_30_L2545AtMallHome": 318, "mobileFeeSubmit": 517, "gesturePatternForget": 70, "relativesGiveMoneyFail": 519, "goodsDtlTab": 520, "468AtLifeChnlPg": 521, "realNameCancel_NewUserAct": 522, "200AtActTheme": 523, "shaidan_checkRules": 371, "strategy_NewUserAct": 516, "bankcard_link_input_cvn2": 525, "shoukuanSetAccount": 526, "pwd_reset_confirm_new_pwd": 415, "F19_3_M1AtMallHome": 528, "UPHceDefaultCardSetActivity": 529, "buyCouponPayAgain": 530, "myPntAtMinePg": 809, "registerCode": 532, "178AtIdxMainPg": 518, "377AtIdxMainPg": 534, "QRBind": 535, "chinaUnicomFeeInquirySuccess": 536, "guidePg_NewYearAct": 537, "login": 538, "openFail_NewYearAct": 539, "485AtHotPay": 540, "markButton_virtual": 290, "mobileContacts": 542, "fukuanOtherIfor": 543, "Applepay": 544, "329AtBanner": 545, "bindcardPayAuthenSubmit": 546, "transferMoneySucc": 667, "goodsTab": 855, "27AtActTheme": 668, "485AtIdxMainPg": 550, "budEditAtTransHP": 551, "F12_2_L2273AtMallHome": 491, "checkbill": 552, "AccountResult": 553, "InMallHome": 670, "YrExpPg": 815, "478AtHotPay": 468, "LoginMobileCheck": 557, "getSoon_P2PActPg": 558, "waterFeePayConfirm": 673, "dtlToAnls": 560, "F15_6_L2520AtMallHome": 561, "goodsHelpSubmit": 562, "creditCardClick": 563, "482AtHotPay": 747, "actCpnDtl": 565, "F7_18_L2540AtMallHome": 566, "paipaicard_eCashRecharge": 567, "click_advert": 568, "F4_13_L2491AtMallHome": 524, "barChartClick": 653, "F16_5_L2395AtMallHome": 569, "btnGift_QPReward": 570, "UPWalletPayActivityProxy": 571, "goodSales": 572, "183AtActTheme": 573, "vMarketingInvtAtMinePg": 574, "707AtActTheme": 575, "orderCpnChoose": 576, "LifeChnlPg": 527, "272AtIdxMainPg": 578, "cloudpayActiveCode": 818, "payAuthCancel_NewUserAct": 37, "transferMoneySubmit": 581, "transDetailApply": 71, "CardScanCheckView": 583, "79AtActTheme": 81, "fukuanScanCode": 585, "B2_194AtMallHomePg": 586, "DefaultCardSetSucc": 587, "myOrderDetail": 588, "488AtActTheme": 589, "326AtActTheme": 117, "MyExpPg": 591, "forgetPasswordMethod": 592, "tdyAtTransHP": 135, "cancelpayment": 533, "F4_15_L2276AtMallHome": 595, "loginSubmit": 597, "logoutConfirm": 598, "shaidan_myHistory": 599, "98AtIdxMainPg": 173, "UPHceActivityInputCardNum": 601, "transDtlRec": 827, "unlockPatternSuccess": 604, "mobileFeePayFail": 605, "F4_15_L2274AtMallHome": 606, "CardManagerView": 607, "city_autoselect": 608, "exchRtCptSucc": 609, "708AtLifeChnlPg": 680, "NewYearActPg": 611, "bankAccountOutConfirm": 612, "F6_23_L2403AtMallHome": 613, "543AtBanner": 614, "RemindView": 615, "TransHP": 618, "377AtActTheme": 619, "loginMeetProblem": 620, "relativesGiveMoneySucc": 621, "BookkeepingOutView": 622, "F20_8_M1AtMallHome": 295, "electricFeePaySuccess": 317, "103brandLst": 311, "ApplySuccess": 626, "electricFeeInquiry": 322, "forgetPasswordBank": 628, "waterFeeInquiry": 629, "497AtLifeChnlPg": 630, "F11_9_M1AtMallHome": 349, "F15_6_L2518AtMallHome": 632, "signAgain_NewYearAct": 633, "agreeApplyCardInfo": 634, "loginFail": 635, "toMerchLst3_QPReward": 541, "AboutView": 637, "chinaTelecomFeeInquiry": 396, "MoreLinkAtOnline": 639, "shoukuanSuccess": 640, "F9_19_M1AtMallHome": 334, "crdBalInqFail": 642, "bindSelectCard": 685, "UPHceCardActivityNew": 644, "98AtBanner": 645, "wantShare_P2PActPg": 646, "P2PLotteryAtPublicPay": 828, "40brandLst": 648, "708AtIdxMainPg": 649, "mobileRechargeRecord": 650, "signClose_NewYearAct": 651, "F7_18_L2052AtMallHome": 652, "chongyang_inviteView_invt": 596, "F9_21_M1AtMallHome": 486, "topright_fukuan": 655, "searchGoods": 245, "132AtLifeChnlPg": 496, "cloudpaySupportBank": 500, "CashBrush": 246, "shoukuanEnter": 641, "I4_159AtMallHomePg": 661, "crdLstAtTransHP": 662, "AccountChBank": 663, "450AtIdxMainPg": 664, "587AtIdxMainPg": 665, "81brandLst": 666, "cloudCardNFC": 547, "F14_4_L2498AtMallHome": 549, "orderApply": 669, "474AtHotPay": 554, "NotificationView": 671, "payAssistant": 672, "goodsDelivery": 559, "B3_192AtMallHomePg": 102, "GesturePwdSetting": 675, "transferAddressBook": 676, "702AtIdxMainPg": 677, "F15_6_M1AtMallHome": 678, "UPHceCouponActivity": 679, "F3_13_M1AtMallHome": 475, "couponClickAtBrandDtl": 610, "loginAtIdxMainPg": 681, "697AtIdxMainPg": 654, "F0FilterOnline": 682, "goodsHelpSuccess": 683, "FilterNative": 684, "quickPassSucc": 643, "480AtHotPay": 686, "79brandLst": 660, "F1_30_M1AtMallHome": 688, "luckMonyAtMinePg": 689, "UPQrShowingActivity": 690, "setPayPasswordSucc": 691, "B2_184AtMallHomePg": 548, "pwd_reset_input_new_pwd": 693, "refind_pwd_get_msg": 692, "paipaicard_eCashRecharge_submit": 695, "bindTakeCardNO": 696, "exchRtCompute": 697, "179AtTopBar": 395, "toMerchLst1_QPReward": 699, "F9_21_L2279AtMallHome": 507, "325AtActTheme": 168, "SecuritySettingView": 702, "326AtIdxMainPg": 631, "F13_4_M1AtMallHome": 616, "registerSuccess": 694, "P2PActPg": 706, "InMyOrderPg": 839, "691AtLifeChnlPg": 707, "electricFeePayConfirm": 708, "toMerchLst2_QPReward": 709, "paipaicard_dectectCard": 710, "172AtActTheme": 711, "close_start_page": 712, "F13_4_L2544AtMallHome": 713, "F7_18_L2053AtMallHome": 714, "toVirtualAcctLst": 715, "F12_2_L2528AtMallHome": 716, "event_id:openBetaFeedbackSubmit": 717, "goodsParaChoose": 451, "695AtIdxMainPg": 719, "F4_15_L2275AtMallHome": 720, "bankDraw_P2PActPg": 721, "I3_157AtMallHomePg": 722, "F17_7_L2501AtMallHome": 723, "backOldVersion": 724, "bindCard": 22, "478AtIdxMainPg": 727, "getSoon_NewYearAct": 728, "481AtHotPay": 729, "myInfoAtMinePg": 730, "D0FilterNative": 698, "SetPatternView": 763, "bankAccountInto": 732, "PayPasswordInput": 733, "gesturePatternOther": 734, "quickPassApply": 735, "couponClickAtStoreDtl": 31, "refind_pwd_msg_submit": 737, "rules_P2PActPg": 738, "bindcardSubmit": 739, "H2_161AtMallHomePg": 701, "B0FilterOnline": 740, "chinaTelecomFeeInquirySuccess": 741, "AddAccountType": 742, "StoreMapView": 743, "F14_6_L2517AtMallHome": 122, "F12_2_M1AtMallHome": 127, "eyeAtTransHP": 746, "F2_30_L2546AtMallHome": 314, "429AtLifeChnlPg": 147, "addCrdAtCrdLstPg": 704, "370AtActTheme": 749, "336AtLifeChnlPg": 750, "350AtHotPay": 751, "MyMessageList": 174, "MyMessageCenter": 582, "shoukuanAccountConfirm": 336, "70AtIdxMainPg": 754, "H3_160AtMallHomePg": 199, "UPHceHomeActivity": 756, "creditCardPayFai": 211, "chinaMobileFeePaySuccess": 758, "bookkeepingSuccess": 219, "480AtLifeChnlPg": 760, "F14_6_L2518AtMallHome": 761, "help_QPReward": 762, "chinaUnicomFeePaySuccess": 564, "370AtIdxMainPg": 764, "toNewVersion": 765, "creditCardRecord": 766, "F3_13_L2489AtMallHome": 767, "openAgain_NewYearAct": 768, "549AtIdxMainPg": 769, "waterFeePaySuccess": 770, "chinaMobileFeeInquiry": 771, "F7_23_M1AtMallHome": 725, "63AtLifeChnlPg": 298, "297AtActTheme": 301, "70AtActTheme": 775, "28AtTransSysPg": 776, "F5_27_L2409AtMallHome": 777, "bindUnionPaySucc": 846, "timeFilterStrt": 779, "133AtActTheme": 216, "352AtActTheme": 781, "safequs_reset_input_pwd": 782, "483AtLifeChnlPg": 783, "F4_15_M1AtMallHome": 784, "302AtIdxMainPg": 785, "457AtIdxMainPg": 780, "fukuan": 786, "saomaPaySuccess": 787, "SearchView": 788, "705AtLifeChnlPg": 789, "HceCardList": 790, "RptAnlsPg": 791, "296AtIdxMainPg": 792, "defaultGoods": 793, "B6_192AtMallHomePg": 794, "waterFeeInquirySuccess": 795, "TransSysPg": 796, "F13_4_L2497AtMallHome": 797, "QrCodePayOrderDetail": 247, "transferIssue": 508, "openBetaAgree": 799, "bindTakeCardNOAgain": 800, "orderSubmit": 801, "creditCardPayAmountCancel": 498, "F16_5_L2468AtMallHome": 803, "MySecuritySettings": 804, "325AtIdxMainPg": 805, "fukuanOverseas": 806, "9AtIdxMainPg": 807, "303AtActTheme": 808, "272AtActTheme": 531, "searchAtIdxMainPg": 810, "TutorialView": 811, "toBankCardDetl": 812, "UPHceActivityListAdd": 813, "fukuanSupportBank": 814, "183AtIdxMainPg": 657, "480AtIdxMainPg": 816, "forgetPasswordApply": 817, "dtlToAnls_virtual": 579, "F4_13_L2490AtMallHome": 819, "reset_welcome_info_submit": 820, "61AtLifeChnlPg": 821, "sysError_P2PAct": 602, "172AtIdxMainPg": 823, "cloudpayElementNext": 577, "crdLstAtIdxMainPg": 824, "450AtActTheme": 825, "708AtBanner": 826, "F15_1_M1AtMallHome": 555, "bankAccountApplyFai": 647, "F16_5_M1AtMallHome": 361, "BookkeepingLineView": 831, "couponsDetail": 832, "openBetaReject": 833, "chinaUnicomFeePayConfirm": 834, "F10_21_L2280AtMallHome": 835, "up99_promotion_share_Moments": 836, "483AtHotPay": 837, "F17_7_M1AtMallHome": 838, "697AtActArea": 718, "201AtIdxMainPg": 840, "paipaicard_inputPwd": 841, "F19_10_L2539AtMallHome": 842, "F13_2_L2530AtMallHome": 305, "custServAtMinePg": 844, "newNative": 845, "F11_9_L2488AtMallHome": 778, "473AtHotPay": 847, "registerSubmit": 848, "F10_21_M1AtMallHome": 849, "F15_1_L2510AtMallHome": 850, "exchRtCptFail": 851, "B4_184AtMallHomePg": 829, "getClose_P2PAct": 853, "139AtBanner": 822, "yrAtTransHP": 659, "765AtLifeChnlPg": 856, "473AtLifeChnlPg": 857, "moduleInLocalService": 858, "F13_2_M1AtMallHome": 859, "F13_2_L2527AtMallHome": 860}